setup.py
geoio/__init__.py
geoio/geoio.py
python_geoio.egg-info/PKG-INFO
python_geoio.egg-info/SOURCES.txt
python_geoio.egg-info/dependency_links.txt
python_geoio.egg-info/top_level.txt